PlatooningSimulator/Core.py
PlatooningSimulator/PlatooningControllers.py
PlatooningSimulator/__init__.py
platooningsimulator-1.0.dist-info/METADATA
platooningsimulator-1.0.dist-info/WHEEL
platooningsimulator-1.0.dist-info/licenses/LICENSE
platooningsimulator-1.0.dist-info/RECORD
