Metadata-Version: 2.1
Name: PlatooningSimulator
Version: 1.0
Summary: A platooning-specific driving simulator, built on top of Carla.
Project-URL: Homepage, https://github.com/karakaron/Platooning_Simulator
Author-email: Aron Karakai <a.karakai@student.rug.nl>
License-File: LICENSE
Classifier: License :: OSI Approved :: BSD License
Classifier: Operating System :: OS Independent
Classifier: Programming Language :: Python :: 3
Requires-Python: >=3.7
Requires-Dist: carla
Requires-Dist: numpy
